{
  "interactionModel": {
    "languageModel": {
      "invocationName": "maxi eighty",
      "intents": [
        {
          "name": "PlayAudio",
          "samples": [
            "play",
            "start",
            "play maxi eighty",
            "play maxi eighty please",
            "start maxi eghty",
            "start maxi eghty please",
            "start the radio",
            "start the radio please",
            "play the radio",
            "play the radio please",
            "start the audio",
            "start the audio please",
            "play the audio",
            "play the audio please",
            "start the music",
            "start the music please",
            "play the music",
            "play the music please"
          ]
        },
        {
          "name": "AMAZON.PauseIntent"
        },
        {
          "name": "AMAZON.ResumeIntent"
        },
        {
          "name": "AMAZON.RepeatIntent"
        },
        {
          "name": "AMAZON.HelpIntent",
          "samples": [
            "help me please",
            "help please",
            "what should i do",
            "what\u0027s next",
            "how can I listen to maxi eighties",
            "how can I listen to maxi eighty",
            "tell me how to play",
            "tell me how to stop",
            "tell me how to resume",
            "how to stop"
          ]
        },
        {
          "name": "AMAZON.StopIntent"
        },
        {
          "name": "AMAZON.CancelIntent"
        },
        {
          "name": "AMAZON.StartOverIntent"
        },
        {
          "name": "AMAZON.NavigateHomeIntent",
          "samples": []
        }
      ]
    }
  },
  "version": "2"
}